{
  "classname": null,
  "name": null,
  "animation": {
    "classname": null,
    "name": "AnimationManager",
    "actionlist": []
  },
  "dataScale": 1,
  "designHeight": 600,
  "designWidth": 960,
  "textures": [
    "ui/UI_Loading.plist",
    "translation_tips.plist",
    "ui/tongyong.plist",
    "translation.plist",
    "betsy_person.plist",
    "zhuguang.plist",
    "ui/ui_btns.plist",
    "ui/UI_Welcome.plist",
    "ui/bottle_mode.plist",
    "ui/UI_Thawy.plist",
    "ui/thawy_items.plist",
    "ui/thawy_animation.plist",
    "ui/UI_AddColor.plist",
    "ui/UI_SelectOrnament.plist",
    "ui/pinsheng.plist",
    "ui/zhuangshi.plist",
    "ui/shouti.plist"
  ],
  "version": "1.2.0.1",
  "widgetTree": {
    "classname": "Panel",
    "name": null,
    "children": [
      {
        "classname": "Button",
        "name": null,
        "children": [],
        "options": {
          "__type": "ComGUIButtonSurrogate:#EditorCommon.JsonModel.Component.GUI",
          "classname": "Button",
          "name": "btnOk",
          "ZOrder": 4,
          "actiontag": 53,
          "anchorPointX": 0.5,
          "anchorPointY": 0.5,
          "classType": null,
          "colorB": 255,
          "colorG": 255,
          "colorR": 255,
          "flipX": false,
          "flipY": false,
          "height": 84,
          "ignoreSize": true,
          "layoutParameter": null,
          "opacity": 255,
          "positionPercentX": 0.7885417,
          "positionPercentY": 0.101666667,
          "positionType": 0,
          "rotation": 0,
          "scaleX": 1,
          "scaleY": 1,
          "sizePercentX": 0.107291669,
          "sizePercentY": 0.06666667,
          "sizeType": 0,
          "tag": 21,
          "touchAble": true,
          "useMergedTexture": false,
          "visible": true,
          "width": 311,
          "x": 757,
          "y": 61,
          "capInsetsHeight": 0,
          "capInsetsWidth": 0,
          "capInsetsX": 0,
          "capInsetsY": 0,
          "disabled": null,
          "disabledData": {
            "path": null,
            "plistFile": null,
            "resourceType": 0
          },
          "fontName": "微软雅黑",
          "fontSize": 14,
          "fontType": 0,
          "normal": null,
          "normalData": {
            "path": "trans_btn_try again0000.png",
            "plistFile": "translation.plist",
            "resourceType": 1
          },
          "pressed": null,
          "pressedData": {
            "path": "trans_btn_try again0001.png",
            "plistFile": "translation.plist",
            "resourceType": 1
          },
          "scale9Enable": false,
          "scale9Height": 84,
          "scale9Width": 311,
          "text": "",
          "textColorB": 255,
          "textColorG": 255,
          "textColorR": 255
        }
      },
      {
        "classname": "ImageView",
        "name": null,
        "children": [
          {
            "classname": "ImageView",
            "name": null,
            "children": [],
            "options": {
              "__type": "ComGUIImageViewSurrogate:#EditorCommon.JsonModel.Component.GUI",
              "classname": "ImageView",
              "name": "eyes",
              "ZOrder": 1,
              "actiontag": 1748,
              "anchorPointX": 0.5,
              "anchorPointY": 0.5,
              "classType": null,
              "colorB": 255,
              "colorG": 255,
              "colorR": 255,
              "flipX": false,
              "flipY": false,
              "height": 76,
              "ignoreSize": true,
              "layoutParameter": null,
              "opacity": 255,
              "positionPercentX": -0.08211144,
              "positionPercentY": 0.3069307,
              "positionType": 0,
              "rotation": 0,
              "scaleX": 1,
              "scaleY": 1,
              "sizePercentX": 0.2346041,
              "sizePercentY": 0.1320132,
              "sizeType": 0,
              "tag": 102,
              "touchAble": false,
              "useMergedTexture": false,
              "visible": true,
              "width": 111,
              "x": -28,
              "y": 186,
              "capInsetsHeight": 0,
              "capInsetsWidth": 0,
              "capInsetsX": 0,
              "capInsetsY": 0,
              "fileName": null,
              "fileNameData": {
                "path": "Betsy2_eyes0000.png",
                "plistFile": "betsy_person.plist",
                "resourceType": 1
              },
              "scale9Enable": false,
              "scale9Height": 76,
              "scale9Width": 111
            }
          }
        ],
        "options": {
          "__type": "ComGUIImageViewSurrogate:#EditorCommon.JsonModel.Component.GUI",
          "classname": "ImageView",
          "name": "betsy_pos",
          "ZOrder": 5,
          "actiontag": 1747,
          "anchorPointX": 0.5,
          "anchorPointY": 0.5,
          "classType": null,
          "colorB": 255,
          "colorG": 255,
          "colorR": 255,
          "flipX": false,
          "flipY": false,
          "height": 606,
          "ignoreSize": true,
          "layoutParameter": null,
          "opacity": 255,
          "positionPercentX": 0.158333331,
          "positionPercentY": 0.398333341,
          "positionType": 0,
          "rotation": 0,
          "scaleX": 1,
          "scaleY": 1,
          "sizePercentX": 0.0833333358,
          "sizePercentY": 0.13333334,
          "sizeType": 0,
          "tag": 101,
          "touchAble": false,
          "useMergedTexture": false,
          "visible": true,
          "width": 341,
          "x": 152,
          "y": 239,
          "capInsetsHeight": 0,
          "capInsetsWidth": 0,
          "capInsetsX": 0,
          "capInsetsY": 0,
          "fileName": null,
          "fileNameData": {
            "path": "Betsy20000.png",
            "plistFile": "betsy_person.plist",
            "resourceType": 1
          },
          "scale9Enable": false,
          "scale9Height": 606,
          "scale9Width": 341
        }
      },
      {
        "classname": "ImageView",
        "name": null,
        "children": [
          {
            "classname": "ImageView",
            "name": null,
            "children": [],
            "options": {
              "__type": "ComGUIImageViewSurrogate:#EditorCommon.JsonModel.Component.GUI",
              "classname": "ImageView",
              "name": "ImageView_1750",
              "ZOrder": 1,
              "actiontag": 1750,
              "anchorPointX": 0.5,
              "anchorPointY": 0.5,
              "classType": null,
              "colorB": 255,
              "colorG": 255,
              "colorR": 255,
              "flipX": false,
              "flipY": false,
              "height": 50,
              "ignoreSize": true,
              "layoutParameter": null,
              "opacity": 255,
              "positionPercentX": 0,
              "positionPercentY": 0.156097561,
              "positionType": 0,
              "rotation": 0,
              "scaleX": 1,
              "scaleY": 1,
              "sizePercentX": 0.238095239,
              "sizePercentY": 0.3902439,
              "sizeType": 0,
              "tag": 179,
              "touchAble": false,
              "useMergedTexture": false,
              "visible": true,
              "width": 224,
              "x": 0,
              "y": 32,
              "capInsetsHeight": 0,
              "capInsetsWidth": 0,
              "capInsetsX": 0,
              "capInsetsY": 0,
              "fileName": null,
              "fileNameData": {
                "path": "trans_result0000.png",
                "plistFile": "translation.plist",
                "resourceType": 1
              },
              "scale9Enable": false,
              "scale9Height": 50,
              "scale9Width": 224
            }
          },
          {
            "classname": "ImageView",
            "name": null,
            "children": [],
            "options": {
              "__type": "ComGUIImageViewSurrogate:#EditorCommon.JsonModel.Component.GUI",
              "classname": "ImageView",
              "name": "ImageView_1781",
              "ZOrder": 2,
              "actiontag": 1781,
              "anchorPointX": 0.5,
              "anchorPointY": 0.5,
              "classType": null,
              "colorB": 255,
              "colorG": 255,
              "colorR": 255,
              "flipX": false,
              "flipY": false,
              "height": 48,
              "ignoreSize": true,
              "layoutParameter": null,
              "opacity": 255,
              "positionPercentX": -0.21726191,
              "positionPercentY": -0.146341458,
              "positionType": 0,
              "rotation": 0,
              "scaleX": 1,
              "scaleY": 1,
              "sizePercentX": 0.238095239,
              "sizePercentY": 0.3902439,
              "sizeType": 0,
              "tag": 176,
              "touchAble": false,
              "useMergedTexture": false,
              "visible": true,
              "width": 58,
              "x": -73,
              "y": -30,
              "capInsetsHeight": 0,
              "capInsetsWidth": 0,
              "capInsetsX": 0,
              "capInsetsY": 0,
              "fileName": null,
              "fileNameData": {
                "path": "clover0000.png",
                "plistFile": "ui/UI_Welcome.plist",
                "resourceType": 1
              },
              "scale9Enable": false,
              "scale9Height": 48,
              "scale9Width": 58
            }
          },
          {
            "classname": "LabelBMFont",
            "name": null,
            "children": [],
            "options": {
              "__type": "ComGUILabelBMFontSurrogate:#EditorCommon.JsonModel.Component.GUI",
              "classname": "LabelBMFont",
              "name": "txt_score",
              "ZOrder": 0,
              "actiontag": 1782,
              "anchorPointX": 0.5,
              "anchorPointY": 0.5,
              "classType": null,
              "colorB": 255,
              "colorG": 255,
              "colorR": 255,
              "flipX": false,
              "flipY": false,
              "height": 32,
              "ignoreSize": true,
              "layoutParameter": null,
              "opacity": 255,
              "positionPercentX": 0.065476194,
              "positionPercentY": -0.09756097,
              "positionType": 0,
              "rotation": 0,
              "scaleX": 0.6999999,
              "scaleY": 0.6999999,
              "sizePercentX": 0,
              "sizePercentY": 0,
              "sizeType": 0,
              "tag": 177,
              "touchAble": false,
              "useMergedTexture": false,
              "visible": true,
              "width": 151,
              "x": 22,
              "y": -20,
              "fileNameData": {
                "path": "font/bmpfont_01.fnt",
                "plistFile": null,
                "resourceType": 0
              },
              "text": "+999"
            }
          }
        ],
        "options": {
          "__type": "ComGUIImageViewSurrogate:#EditorCommon.JsonModel.Component.GUI",
          "classname": "ImageView",
          "name": "txt_mc",
          "ZOrder": 5,
          "actiontag": 1749,
          "anchorPointX": 0.5,
          "anchorPointY": 0.5,
          "classType": null,
          "colorB": 255,
          "colorG": 255,
          "colorR": 255,
          "flipX": false,
          "flipY": false,
          "height": 205,
          "ignoreSize": true,
          "layoutParameter": null,
          "opacity": 255,
          "positionPercentX": 0.35625,
          "positionPercentY": 0.8183333,
          "positionType": 0,
          "rotation": 0,
          "scaleX": 1,
          "scaleY": 1,
          "sizePercentX": 0.0833333358,
          "sizePercentY": 0.13333334,
          "sizeType": 0,
          "tag": 178,
          "touchAble": false,
          "useMergedTexture": false,
          "visible": true,
          "width": 336,
          "x": 342,
          "y": 491,
          "capInsetsHeight": 0,
          "capInsetsWidth": 0,
          "capInsetsX": 0,
          "capInsetsY": 0,
          "fileName": null,
          "fileNameData": {
            "path": "message 10000.png",
            "plistFile": "ui/UI_Welcome.plist",
            "resourceType": 1
          },
          "scale9Enable": false,
          "scale9Height": 205,
          "scale9Width": 336
        }
      },
      {
        "classname": "Panel",
        "name": null,
        "children": [
          {
            "classname": "ImageView",
            "name": null,
            "children": [],
            "options": {
              "__type": "ComGUIImageViewSurrogate:#EditorCommon.JsonModel.Component.GUI",
              "classname": "ImageView",
              "name": "ImageView_130",
              "ZOrder": 5,
              "actiontag": 130,
              "anchorPointX": 0.5,
              "anchorPointY": 0.5,
              "classType": null,
              "colorB": 255,
              "colorG": 255,
              "colorR": 255,
              "flipX": false,
              "flipY": false,
              "height": 706,
              "ignoreSize": true,
              "layoutParameter": null,
              "opacity": 255,
              "positionPercentX": 3.35,
              "positionPercentY": 2.09,
              "positionType": 0,
              "rotation": 0,
              "scaleX": 0.85,
              "scaleY": 0.85,
              "sizePercentX": 0.4,
              "sizePercentY": 0.4,
              "sizeType": 0,
              "tag": 80,
              "touchAble": false,
              "useMergedTexture": false,
              "visible": true,
              "width": 641,
              "x": 670,
              "y": 418,
              "capInsetsHeight": 0,
              "capInsetsWidth": 0,
              "capInsetsX": 0,
              "capInsetsY": 0,
              "fileName": null,
              "fileNameData": {
                "path": "ui/UI_End.png",
                "plistFile": null,
                "resourceType": 0
              },
              "scale9Enable": false,
              "scale9Height": 706,
              "scale9Width": 641
            }
          }
        ],
        "options": {
          "__type": "ComGUIPanelSurrogate:#EditorCommon.JsonModel.Component.GUI",
          "classname": "Panel",
          "name": "bgBig",
          "ZOrder": 2,
          "actiontag": 1783,
          "anchorPointX": 0,
          "anchorPointY": 0,
          "classType": null,
          "colorB": 255,
          "colorG": 255,
          "colorR": 255,
          "flipX": false,
          "flipY": false,
          "height": 200,
          "ignoreSize": false,
          "layoutParameter": null,
          "opacity": 255,
          "positionPercentX": 0,
          "positionPercentY": 0,
          "positionType": 0,
          "rotation": 0,
          "scaleX": 1,
          "scaleY": 1,
          "sizePercentX": 0.208333328,
          "sizePercentY": 0.333333343,
          "sizeType": 0,
          "tag": 178,
          "touchAble": false,
          "useMergedTexture": false,
          "visible": true,
          "width": 200,
          "x": 0,
          "y": 0,
          "backGroundImage": null,
          "backGroundImageData": null,
          "backGroundScale9Enable": false,
          "bgColorB": 255,
          "bgColorG": 200,
          "bgColorOpacity": 100,
          "bgColorR": 150,
          "bgEndColorB": 255,
          "bgEndColorG": 200,
          "bgEndColorR": 150,
          "bgStartColorB": 255,
          "bgStartColorG": 255,
          "bgStartColorR": 255,
          "capInsetsHeight": 0,
          "capInsetsWidth": 0,
          "capInsetsX": 0,
          "capInsetsY": 0,
          "clipAble": false,
          "colorType": 0,
          "layoutType": 0,
          "vectorX": 0,
          "vectorY": -0.5
        }
      },
      {
        "classname": "ImageView",
        "name": null,
        "children": [
          {
            "classname": "LabelBMFont",
            "name": null,
            "children": [],
            "options": {
              "__type": "ComGUILabelBMFontSurrogate:#EditorCommon.JsonModel.Component.GUI",
              "classname": "LabelBMFont",
              "name": "moneytxt",
              "ZOrder": 0,
              "actiontag": 1785,
              "anchorPointX": 0.5,
              "anchorPointY": 0.5,
              "classType": null,
              "colorB": 255,
              "colorG": 255,
              "colorR": 255,
              "flipX": false,
              "flipY": false,
              "height": 32,
              "ignoreSize": true,
              "layoutParameter": null,
              "opacity": 255,
              "positionPercentX": 0.206349209,
              "positionPercentY": 0.109090909,
              "positionType": 0,
              "rotation": 0,
              "scaleX": 0.399999917,
              "scaleY": 0.399999917,
              "sizePercentX": 0,
              "sizePercentY": 0,
              "sizeType": 0,
              "tag": 180,
              "touchAble": false,
              "useMergedTexture": false,
              "visible": true,
              "width": 148,
              "x": 26,
              "y": 6,
              "fileNameData": {
                "path": "font/bmpfont_01.fnt",
                "plistFile": null,
                "resourceType": 0
              },
              "text": "9999"
            }
          }
        ],
        "options": {
          "__type": "ComGUIImageViewSurrogate:#EditorCommon.JsonModel.Component.GUI",
          "classname": "ImageView",
          "name": "money",
          "ZOrder": 5,
          "actiontag": 1784,
          "anchorPointX": 0.5,
          "anchorPointY": 0.5,
          "classType": null,
          "colorB": 255,
          "colorG": 255,
          "colorR": 255,
          "flipX": false,
          "flipY": false,
          "height": 55,
          "ignoreSize": true,
          "layoutParameter": null,
          "opacity": 255,
          "positionPercentX": 0.08958333,
          "positionPercentY": 0.9216667,
          "positionType": 0,
          "rotation": 0,
          "scaleX": 1,
          "scaleY": 1,
          "sizePercentX": 0.0833333358,
          "sizePercentY": 0.13333334,
          "sizeType": 0,
          "tag": 16,
          "touchAble": false,
          "useMergedTexture": false,
          "visible": true,
          "width": 126,
          "x": 86,
          "y": 553,
          "capInsetsHeight": 0,
          "capInsetsWidth": 0,
          "capInsetsX": 0,
          "capInsetsY": 0,
          "fileName": null,
          "fileNameData": {
            "path": "bigMoneyBar0000.png",
            "plistFile": "ui/ui_btns.plist",
            "resourceType": 1
          },
          "scale9Enable": false,
          "scale9Height": 55,
          "scale9Width": 126
        }
      }
    ],
    "options": {
      "__type": "ComGUIPanelSurrogate:#EditorCommon.JsonModel.Component.GUI",
      "classname": "Panel",
      "name": "Panel_999",
      "ZOrder": 0,
      "actiontag": -1,
      "anchorPointX": 0,
      "anchorPointY": 0,
      "classType": null,
      "colorB": 255,
      "colorG": 255,
      "colorR": 255,
      "flipX": false,
      "flipY": false,
      "height": 600,
      "ignoreSize": false,
      "layoutParameter": null,
      "opacity": 255,
      "positionPercentX": 0,
      "positionPercentY": 0,
      "positionType": 0,
      "rotation": 0,
      "scaleX": 1,
      "scaleY": 1,
      "sizePercentX": 1,
      "sizePercentY": 1,
      "sizeType": 0,
      "tag": 15,
      "touchAble": false,
      "useMergedTexture": false,
      "visible": true,
      "width": 960,
      "x": 0,
      "y": 0,
      "backGroundImage": null,
      "backGroundImageData": {
        "path": "bg.png",
        "plistFile": null,
        "resourceType": 0
      },
      "backGroundScale9Enable": false,
      "bgColorB": 255,
      "bgColorG": 200,
      "bgColorOpacity": 0,
      "bgColorR": 150,
      "bgEndColorB": 255,
      "bgEndColorG": 200,
      "bgEndColorR": 150,
      "bgStartColorB": 255,
      "bgStartColorG": 255,
      "bgStartColorR": 255,
      "capInsetsHeight": 0,
      "capInsetsWidth": 0,
      "capInsetsX": 0,
      "capInsetsY": 0,
      "clipAble": false,
      "colorType": 1,
      "layoutType": 0,
      "vectorX": 0,
      "vectorY": -0.5
    }
  }
}