{ "height":5,
 "layers":[
        {
         "data":[0, 0, 0, 41, 0, 46, 8, 7, 6, 0, 0, 3, 11, 7, 24, 22, 8, 8, 6, 6, 0, 0, 34, 6, 8],
         "height":5,
         "name":"start_path",
         "opacity":1,
         "type":"tilelayer",
         "visible":true,
         "width":5,
         "x":0,
         "y":0
        }, 
        {
         "data":[0, 0, 0, 0, 0, 0, 0, 0, 0, 0, 0, 0, 0, 0, 0, 0, 0, 0, 0, 0, 0, 0, 0, 0, 0],
         "height":5,
         "name":"correct_path",
         "opacity":1,
         "type":"tilelayer",
         "visible":true,
         "width":5,
         "x":0,
         "y":0
        }, 
        {
         "data":[0, 0, 0, 0, 0, 0, 0, 0, 0, 0, 0, 0, 0, 0, 18, 0, 0, 0, 0, 0, 0, 0, 13, 0, 0],
         "height":5,
         "name":"goal_0",
         "opacity":1,
         "properties":
            {
             "moves":11,
             "statsType":3,
             "time":-1
            },
         "propertytypes":
            {
             "moves":"int",
             "statsType":"int",
             "time":"int"
            },
         "type":"tilelayer",
         "visible":true,
         "width":5,
         "x":0,
         "y":0
        }, 
        {
         "data":[0, 0, 0, 0, 0, 0, 0, 0, 0, 0, 0, 0, 0, 0, 13, 18, 0, 0, 0, 0, 0, 0, 0, 0, 0],
         "height":5,
         "name":"goal_1",
         "opacity":1,
         "properties":
            {
             "moves":6,
             "statsType":3,
             "time":-1
            },
         "propertytypes":
            {
             "moves":"int",
             "statsType":"int",
             "time":"int"
            },
         "type":"tilelayer",
         "visible":true,
         "width":5,
         "x":0,
         "y":0
        }, 
        {
         "data":[0, 0, 0, 0, 0, 18, 0, 0, 0, 0, 0, 0, 0, 0, 0, 13, 0, 0, 0, 0, 0, 0, 0, 0, 0],
         "height":5,
         "name":"goal_2",
         "opacity":1,
         "properties":
            {
             "moves":2,
             "statsType":3,
             "time":-1
            },
         "propertytypes":
            {
             "moves":"int",
             "statsType":"int",
             "time":"int"
            },
         "type":"tilelayer",
         "visible":true,
         "width":5,
         "x":0,
         "y":0
        }, 
        {
         "data":[0, 0, 0, 18, 0, 13, 0, 0, 0, 0, 0, 0, 0, 0, 0, 0, 0, 0, 0, 0, 0, 0, 0, 0, 0],
         "height":5,
         "name":"goal_3",
         "opacity":1,
         "properties":
            {
             "moves":8,
             "statsType":1,
             "time":-1
            },
         "propertytypes":
            {
             "moves":"int",
             "statsType":"int",
             "time":"int"
            },
         "type":"tilelayer",
         "visible":true,
         "width":5,
         "x":0,
         "y":0
        }],
 "nextobjectid":24,
 "orientation":"isometric",
 "renderorder":"right-down",
 "tileheight":170,
 "tilesets":[
        {
         "firstgid":1,
         "source":"..\/tiled\/tiles-0.tsx"
        }, 
        {
         "firstgid":33,
         "source":"..\/tiled\/tiles-1.tsx"
        }, 
        {
         "firstgid":65,
         "source":"..\/tiled\/tiles-2.tsx"
        }, 
        {
         "firstgid":97,
         "source":"..\/tiled\/tiles-3.tsx"
        }],
 "tilewidth":232,
 "version":1,
 "width":5
}